watcher/__init__.py
watcher/arguments.py
watcher/event.py
watcher/text_formatting.py
watcher/watcher.py
watcher_cli-0.1.0.dist-info/LICENSE
watcher_cli-0.1.0.dist-info/METADATA
watcher_cli-0.1.0.dist-info/WHEEL
watcher_cli-0.1.0.dist-info/entry_points.txt
watcher_cli-0.1.0.dist-info/top_level.txt
watcher_cli-0.1.0.dist-info/RECORD
