Metadata-Version: 2.1
Name: watcher-cli
Version: 0.1.0
Summary: A watcher for running python code when after every modification
Author-email: NathanGavenski <nathangavenski@gmail.com>
License: MIT
Project-URL: homepage, https://github.com/NathanGavenski/python-watcher
Project-URL: documentation, https://github.com/NathanGavenski/python-watcher
Project-URL: repository, https://github.com/NathanGavenski/python-watcher
Classifier: License :: OSI Approved :: MIT License
Classifier: Programming Language :: Python :: 3.10
Classifier: Operating System :: OS Independent
Requires-Python: >=3.10
License-File: LICENSE
Requires-Dist: watchdog
Provides-Extra: dev
Requires-Dist: pytest; extra == "dev"
Requires-Dist: twine; extra == "dev"
Requires-Dist: build; extra == "dev"
